lib_list/__init__.py
lib_list/__init__conf__.py
lib_list/lib_list.py
lib_list/lib_list_cli.py
lib_list/py.typed
lib_list-1.1.9.dist-info/LICENSE
lib_list-1.1.9.dist-info/METADATA
lib_list-1.1.9.dist-info/WHEEL
lib_list-1.1.9.dist-info/entry_points.txt
lib_list-1.1.9.dist-info/top_level.txt
lib_list-1.1.9.dist-info/RECORD
